scimma_client-0.0.4-py3.6-nspkg.pth
scimma/client/__init__.py
scimma/client/__main__.py
scimma/client/_version.py
scimma/client/publish.py
scimma_client-0.0.4.dist-info/LICENSE
scimma_client-0.0.4.dist-info/METADATA
scimma_client-0.0.4.dist-info/WHEEL
scimma_client-0.0.4.dist-info/entry_points.txt
scimma_client-0.0.4.dist-info/namespace_packages.txt
scimma_client-0.0.4.dist-info/top_level.txt
scimma_client-0.0.4.dist-info/RECORD
